MANIFEST.in
README.rst
setup.py
grader/__init__.py
grader/configobj.py
grader/configobj.pyc
grader/grader.py
grader/grader.py~
grader.egg-info/PKG-INFO
grader.egg-info/SOURCES.txt
grader.egg-info/dependency_links.txt
grader.egg-info/entry_points.txt
grader.egg-info/top_level.txt
grader/skeleton_grader/grader.bat
grader/skeleton_grader/grader.sh
grader/skeleton_grader/log.txt
grader/skeleton_grader/settings.conf
grader/skeleton_grader/students.txt
grader/skeleton_grader/samples/grader.bat
grader/skeleton_grader/samples/grader.sh
grader/skeleton_grader/samples/settings.conf
grader/skeleton_grader/samples/students.txt
grader/skeleton_grader/samples/grader_files/naranjo project 3/naranjo exercise 1.3dm
grader/skeleton_grader/samples/grader_files/naranjo project 3/naranjo exercise 1.jpg
grader/skeleton_grader/samples/grader_files/oglesby project 3/oglesby exercise 1.3dm
grader/skeleton_grader/samples/grader_files/oglesby project 3/oglesby exercise 1.jpg
grader/skeleton_grader/samples/grader_files/simpson project 3/simpson exercise 1.jpg