Metadata-Version: 1.1
Name: grader
Version: 1.2
Summary: A homework checker for a 3d Modeling class
Home-page: https://github.com/doubledubba/grader
Author: Jose Luis Naranjo Gomez
Author-email: luisnaranjo733@hotmail.com
License: GNU GPL
Platform: UNKNOWN
Classifier: License :: OSI Approved :: GNU General Public License (GPL)
Classifier: Topic :: Utilities
